lexe_wrapper/__init__.py
lexe_wrapper/__main__.py
lexe_wrapper/manager.py
lexe_wrapper-2.2.2.dist-info/METADATA
lexe_wrapper-2.2.2.dist-info/WHEEL
lexe_wrapper-2.2.2.dist-info/top_level.txt
lexe_wrapper-2.2.2.dist-info/entry_points.txt
lexe_wrapper-2.2.2.dist-info/RECORD
