Metadata-Version: 2.1
Name: lexe-wrapper
Version: 2.2.2
Summary: Unofficial, open-source Python wrapper for Lexe Bitcoin Lightning Network wallet integration
Home-page: https://github.com/lexe-app/lexe-wrapper
Author: Mat Balez
Author-email: matbalez@gmail.com
License: MIT
Requires-Python: >=3.7
Requires-Dist: requests>=2.31.0
Classifier: Development Status :: 5 - Production/Stable
Classifier: Intended Audience :: Developers
Classifier: License :: OSI Approved :: MIT License
Classifier: Programming Language :: Python :: 3
